dicom_ecg_plot-1.3.5.data/scripts/dicom-ecg-plot
dicom_ecg_plot-1.3.5.dist-info/licenses/LICENSE
ecg/__init__.py
ecg/ecg.py
ecg/i18n.py
ecg/improved_ecg_module.py
dicom_ecg_plot-1.3.5.dist-info/METADATA
dicom_ecg_plot-1.3.5.dist-info/WHEEL
dicom_ecg_plot-1.3.5.dist-info/top_level.txt
dicom_ecg_plot-1.3.5.dist-info/RECORD
