Metadata-Version: 2.4
Name: dicom-ecg-plot
Version: 1.3.5
Summary: Plot Dicom ECG Waveforms
Home-page: https://github.com/marcodebe/dicomecg_convert
Author: Marco De Benedetto
Author-email: debe@galliera.it
Classifier: License :: OSI Approved :: MIT License
Classifier: Programming Language :: Python :: 2.7
Classifier: Programming Language :: Python :: 3
Classifier: Topic :: Scientific/Engineering :: Medical Science Apps.
Classifier: Intended Audience :: Healthcare Industry
License-File: LICENSE
Requires-Dist: pydicom>=1.0.1
Requires-Dist: numpy
Requires-Dist: matplotlib
Requires-Dist: scipy
Requires-Dist: docopt
Requires-Dist: requests
Dynamic: author
Dynamic: author-email
Dynamic: classifier
Dynamic: description
Dynamic: description-content-type
Dynamic: home-page
Dynamic: license-file
Dynamic: requires-dist
Dynamic: summary
